md2pdf_client/__init__.py
md2pdf_client/__version__.py
md2pdf_client/md2pdf_client.py
md2pdf_client/shortcut_win32.py
md2pdf_client-1.3.3.dist-info/LICENSE
md2pdf_client-1.3.3.dist-info/METADATA
md2pdf_client-1.3.3.dist-info/WHEEL
md2pdf_client-1.3.3.dist-info/entry_points.txt
md2pdf_client-1.3.3.dist-info/top_level.txt
md2pdf_client-1.3.3.dist-info/RECORD
