Metadata-Version: 2.1
Name: md2pdf-client
Version: 1.3.3
Summary: Client for using an md2pdf server to render Markdown text into a pretty PDF
Home-page: https://gitlab.com/md2x/md2pdf-client
Author: Sean Lanigan
License: GNU Affero General Public License v3 or later
Platform: UNKNOWN
Classifier: Programming Language :: Python :: 3
Classifier: License :: OSI Approved :: GNU Affero General Public License v3 or later (AGPLv3+)
Classifier: Operating System :: OS Independent
Classifier: Development Status :: 4 - Beta
Classifier: Topic :: Office/Business
Classifier: Intended Audience :: End Users/Desktop
Requires-Python: >=3.4, <4
Requires-Dist: ruamel.yaml (>=0.15)
Requires-Dist: requests (>=2.9)
Requires-Dist: pywin32 ; platform_system == "Windows"
